{
  "eventId": 109,
  "fullName": "Be Happiness!!!! - HAPPY BMS EVENT -",
  "abbrevName": "",
  "shortName": "",
  "title": "Be Happiness!!!! - HAPPY BMS EVENT -",
  "description": "",
  "bannerType1": "https://manbow.nothing.sh/event/images/109.jpg",
  "registrationStart": "2016-07-02T00:00:00+09:00",
  "registrationEnd": "2016-07-03T00:00:00+09:00",
  "impressionStart": "2016-07-04T00:00:00+09:00",
  "impressionEnd": "2016-07-17T00:00:00+09:00",
  "periodStart": "2016-07-02T00:00:00+09:00",
  "periodEnd": "2016-07-17T00:00:00+09:00",
  "entryCount": 39,
  "impressionCount": 941,
  "infoLink": "http://nextreflection.net/behappiness/",
  "detailLink": "https://manbow.nothing.sh/event/event.cgi?action=Details&event=109",
  "listLink": "https://manbow.nothing.sh/event/event.cgi?action=List_def&event=109",
  "teamListLink": "",
  "isBof": false,
  "logoType1": "",
  "logoType2": "",
  "logoType3": "",
  "logoType4": "",
  "logoType5": "",
  "titleJpg": "",
  "bannerType2": "",
  "video": "",
  "headerJpg": "",
  "headerPng": "",
  "backJpg": "",
  "backPng": "",
  "isModern": false,
  "isPreModern": false,
  "hasModernList": false,
  "testString": "",
  "testStringArray": null,
  "teams": null
}
