{
  "eventId": 135,
  "fullName": "MUMEI Academy 2021",
  "abbrevName": "",
  "shortName": "",
  "title": "MUMEI Academy 2021",
  "description": "",
  "bannerType1": "https://manbow.nothing.sh/event/images/135.jpg",
  "registrationStart": "2021-05-20T00:00:00+09:00",
  "registrationEnd": "2021-05-31T00:00:00+09:00",
  "impressionStart": "2021-06-01T00:00:00+09:00",
  "impressionEnd": "2021-07-05T00:00:00+09:00",
  "periodStart": "2021-05-20T00:00:00+09:00",
  "periodEnd": "2021-07-05T00:00:00+09:00",
  "entryCount": 81,
  "impressionCount": 5349,
  "infoLink": "https://mumeiacademy.com/2021/",
  "detailLink": "https://manbow.nothing.sh/event/event.cgi?action=Details&event=135",
  "listLink": "https://manbow.nothing.sh/event/event.cgi?action=List_def&event=135",
  "teamListLink": "",
  "isBof": false,
  "logoType1": "",
  "logoType2": "",
  "logoType3": "",
  "logoType4": "",
  "logoType5": "",
  "titleJpg": "",
  "bannerType2": "",
  "video": "",
  "headerJpg": "",
  "headerPng": "",
  "backJpg": "",
  "backPng": "",
  "isModern": false,
  "isPreModern": false,
  "hasModernList": false,
  "testString": "",
  "testStringArray": null,
  "teams": null
}
