{
  "id": 62,
  "fullName": "ChaosStage",
  "abbrevName": "",
  "shortName": "",
  "title": "ChaosStage",
  "description": "",
  "bannerType1": "https://manbow.nothing.sh/event/images/62.jpg",
  "registrationStart": "2010-02-20T00:00:00+09:00",
  "registrationEnd": "2010-02-21T00:00:00+09:00",
  "impressionStart": "2010-02-22T00:00:00+09:00",
  "impressionEnd": "2010-03-07T00:00:00+09:00",
  "periodStart": "2010-02-20T00:00:00+09:00",
  "periodEnd": "2010-03-07T00:00:00+09:00",
  "entryCount": 14,
  "impressionCount": 381,
  "infoLink": "http://scytheleg.bms.ms/tempyou/event/chaos/",
  "detailLink": "https://manbow.nothing.sh/event/event.cgi?action=Details&event=62",
  "listLink": "https://manbow.nothing.sh/event/event.cgi?action=List_def&event=62",
  "isBof": false,
  "logoType1": "",
  "logoType2": "",
  "logoType3": "",
  "logoType4": "",
  "logoType5": "",
  "titleJpg": "",
  "bannerType2": "",
  "video": "",
  "headerJpg": "",
  "headerPng": "",
  "backJpg": "",
  "backPng": "",
  "isModern": false,
  "teams": null
}
