{
  "eventId": 106,
  "fullName": "BMS Charater Respect Party 2016",
  "abbrevName": "",
  "shortName": "",
  "title": "BMS Charater Respect Party 2016",
  "description": "",
  "bannerType1": "https://manbow.nothing.sh/event/images/106.jpg",
  "registrationStart": "2016-01-16T00:00:00+09:00",
  "registrationEnd": "2016-01-31T00:00:00+09:00",
  "impressionStart": "2016-01-23T00:00:00+09:00",
  "impressionEnd": "2016-02-07T00:00:00+09:00",
  "periodStart": "2016-01-16T00:00:00+09:00",
  "periodEnd": "2016-02-07T00:00:00+09:00",
  "entryCount": 9,
  "impressionCount": 90,
  "infoLink": "http://bcrp2016.web.fc2.com/",
  "detailLink": "https://manbow.nothing.sh/event/event.cgi?action=Details&event=106",
  "listLink": "https://manbow.nothing.sh/event/event.cgi?action=List_def&event=106",
  "teamListLink": "",
  "isBof": false,
  "logoType1": "",
  "logoType2": "",
  "logoType3": "",
  "logoType4": "",
  "logoType5": "",
  "titleJpg": "",
  "bannerType2": "",
  "video": "",
  "headerJpg": "",
  "headerPng": "",
  "backJpg": "",
  "backPng": "",
  "isModern": false,
  "isPreModern": false,
  "hasModernList": false,
  "testString": "",
  "testStringArray": null,
  "teams": null
}
