{
  "id": 91,
  "fullName": "Wire Puller 3",
  "abbrevName": "",
  "shortName": "",
  "title": "Wire Puller 3",
  "description": "",
  "bannerType1": "https://manbow.nothing.sh/event/images/91.jpg",
  "registrationStart": "2014-02-01T00:00:00+09:00",
  "registrationEnd": "2014-02-02T00:00:00+09:00",
  "impressionStart": "2014-02-03T00:00:00+09:00",
  "impressionEnd": "2014-02-23T00:00:00+09:00",
  "periodStart": "2014-02-01T00:00:00+09:00",
  "periodEnd": "2014-02-23T00:00:00+09:00",
  "entryCount": 34,
  "impressionCount": 562,
  "infoLink": "http://railroad.moto-chika.com/wirepuller3.html",
  "detailLink": "https://manbow.nothing.sh/event/event.cgi?action=Details&event=91",
  "listLink": "https://manbow.nothing.sh/event/event.cgi?action=List_def&event=91",
  "isBof": false,
  "logoType1": "",
  "logoType2": "",
  "logoType3": "",
  "logoType4": "",
  "logoType5": "",
  "titleJpg": "",
  "bannerType2": "",
  "video": "",
  "headerJpg": "",
  "headerPng": "",
  "backJpg": "",
  "backPng": "",
  "isModern": false,
  "teams": null
}
